<Comment>
  <_id>5c3a3a15a4f2271887d85515</_id>
  <familia>
    <familia>
      <_id>5c3a3a15a4f2271887d85516</_id>
      <selfId>13</selfId>
      <nombre>familia drohne5</nombre>
      <personas>
        <personas>
          <_id>5c3a3a15a4f2271887d85517</_id>
          <selfId>9</selfId>
          <familyId>13</familyId>
          <nombre>drohne</nombre>
          <correo></correo>
          <password></password>
          <id>
            <timestamp>1547319829</timestamp>
            <machineIdentifier>10809895</machineIdentifier>
            <processIdentifier>6279</processIdentifier>
            <counter>14177559</counter>
            <time>1547319829000</time>
            <date>1547319829000</date>
            <timeSecond>1547319829</timeSecond>
          </id>
        </personas>
      </personas>
      <id>
        <timestamp>1547319829</timestamp>
        <machineIdentifier>10809895</machineIdentifier>
        <processIdentifier>6279</processIdentifier>
        <counter>14177558</counter>
        <time>1547319829000</time>
        <date>1547319829000</date>
        <timeSecond>1547319829</timeSecond>
      </id>
    </familia>
  </familia>
  <titulo>Erase una segunda vez</titulo>
  <texto>Pues si pues si </texto>
  <persona>
    <persona>
      <_id>5c3a3a15a4f2271887d85518</_id>
      <selfId>8</selfId>
      <familyId>1</familyId>
      <nombre>drohne</nombre>
      <correo>drohne@gmail.com</correo>
      <password>drohne</password>
      <id>
        <timestamp>1547319829</timestamp>
        <machineIdentifier>10809895</machineIdentifier>
        <processIdentifier>6279</processIdentifier>
        <counter>14177560</counter>
        <time>1547319829000</time>
        <date>1547319829000</date>
        <timeSecond>1547319829</timeSecond>
      </id>
    </persona>
  </persona>
  <selfId>4</selfId>
  <fecha>1546300800000</fecha>
  <id>
    <timestamp>1547319829</timestamp>
    <machineIdentifier>10809895</machineIdentifier>
    <processIdentifier>6279</processIdentifier>
    <counter>14177557</counter>
    <time>1547319829000</time>
    <date>1547319829000</date>
    <timeSecond>1547319829</timeSecond>
  </id>
</Comment>
